django_azure_backup/__init__.py
django_azure_backup/admin.py
django_azure_backup/apps.py
django_azure_backup/models.py
django_azure_backup/tests.py
django_azure_backup/views.py
django_azure_backup/db/__init__.py
django_azure_backup/db/base.py
django_azure_backup/management/__init__.py
django_azure_backup/management/commands/__init__.py
django_azure_backup/management/commands/db-backup-list.py
django_azure_backup/management/commands/db-backup.py
django_azure_backup/management/commands/db-restore.py
django_azure_backup/migrations/__init__.py
django_azure_backup-0.0.5.dist-info/LICENSE
django_azure_backup-0.0.5.dist-info/METADATA
django_azure_backup-0.0.5.dist-info/WHEEL
django_azure_backup-0.0.5.dist-info/top_level.txt
django_azure_backup-0.0.5.dist-info/RECORD
