Metadata-Version: 2.1
Name: django-azure-backup
Version: 0.0.5
Summary: postgres backup database with cloud upload.
Home-page: https://github.com/GlibAI/rewa_backup/
Author: Ajit Mourya
Author-email: ajit@glib.ai
License: UNKNOWN
Platform: UNKNOWN
Classifier: Programming Language :: Python :: 3
Classifier: License :: OSI Approved :: MIT License
Classifier: Operating System :: OS Independent
Requires-Python: >=3.6
License-File: LICENSE
Requires-Dist: django-storages[azure]
